Workbook

Sheet INICIO
B2: KAIPRO | Dashboard Integral de Gestión Empresarial
B3: Versión Demo · Actualizable con tus datos reales
B5: ◆ RESUMEN EJECUTIVO — INDICADORES CLAVE
B6: VENTAS MES | D6: COSTO TOTAL | F6: MARGEN NETO | H6: EFICIENCIA | J6: STOCK VALOR | L6: FLUJO NETO
B7: =PRODUCCION!Q30 -> 3981000 | D7: =FINANZAS!E35 -> 8.977914 | F7: =RENTABILIDAD!H28 -> 0.34453333 | H7: =PRODUCCION!S9 -> 0.99005223 | J7: =INVENTARIO!F32 -> 51512.5 | L7: =FINANZAS!E38 -> 1778169.9
B10: VENTAS VS META MENSUAL | J10: SEMÁFORO DE INDICADORES
B11: Mes | C11: Ventas | D11: Meta | E11: Var $ | F11: Var % | G11: Estado | J11: Indicador | K11: Valor | L11: Semáforo
B12: Ene | C12: 42000 | D12: 40000 | E12: =C12-D12 -> 2000 | F12: =IF(D12=0,0,(C12-D12)/D12) -> 0.05 | G12: =IF(C12>=D12,"✔ OK","✘ Bajo") -> ✔ OK | J12: Eficiencia Producción | K12: =PRODUCCION!S9 -> 0.99005223 | L12: =IF(K12>=0.85,"🟢 BIEN",IF(K12>=0.75,"🟡 ALERTA","🔴 CRÍTICO")) -> 🟢 BIEN
B13: Feb | C13: 45500 | D13: 43000 | E13: =C13-D13 -> 2500 | F13: =IF(D13=0,0,(C13-D13)/D13) -> 0.058139535 | G13: =IF(C13>=D13,"✔ OK","✘ Bajo") -> ✔ OK | J13: Margen Bruto | K13: =RENTABILIDAD!H25 -> 0.31436093 | L13: =IF(K13>=0.35,"🟢 BIEN",IF(K13>=0.25,"🟡 ALERTA","🔴 CRÍTICO")) -> 🟡 ALERTA
B14: Mar | C14: 41200 | D14: 43000 | E14: =C14-D14 -> -1800 | F14: =IF(D14=0,0,(C14-D14)/D14) -> -0.041860465 | G14: =IF(C14>=D14,"✔ OK","✘ Bajo") -> ✘ Bajo | J14: Rotación Inventario | K14: =INVENTARIO!G32 -> 4.4556396 | L14: =IF(K14>=4,"🟢 BIEN",IF(K14>=2.5,"🟡 ALERTA","🔴 CRÍTICO")) -> 🟢 BIEN
B15: Abr | C15: 48000 | D15: 46000 | E15: =C15-D15 -> 2000 | F15: =IF(D15=0,0,(C15-D15)/D15) -> 0.043478261 | G15: =IF(C15>=D15,"✔ OK","✘ Bajo") -> ✔ OK | J15: Cobertura Stock (días) | K15: =INVENTARIO!H32 -> 91.25 | L15: =IF(K15>=30,"🟢 BIEN",IF(K15>=15,"🟡 ALERTA","🔴 CRÍTICO")) -> 🟢 BIEN
B16: May | C16: 51000 | D16: 48000 | E16: =C16-D16 -> 3000 | F16: =IF(D16=0,0,(C16-D16)/D16) -> 0.0625 | G16: =IF(C16>=D16,"✔ OK","✘ Bajo") -> ✔ OK | J16: Flujo Operativo | K16: =FINANZAS!E38 -> 1778169.9 | L16: =IF(K16>=1,"🟢 BIEN",IF(K16>=0,"🟡 ALERTA","🔴 CRÍTICO")) -> 🟢 BIEN
B17: Jun | C17: 49500 | D17: 50000 | E17: =C17-D17 -> -500 | F17: =IF(D17=0,0,(C17-D17)/D17) -> -0.01 | G17: =IF(C17>=D17,"✔ OK","✘ Bajo") -> ✘ Bajo | J17: Cumpl. Ventas | K17: =PRODUCCION!T9 -> 0.99005223 | L17: =IF(K17>=0.95,"🟢 BIEN",IF(K17>=0.85,"🟡 ALERTA","🔴 CRÍTICO")) -> 🟢 BIEN
B45: ℹ CÓMO USAR ESTE ARCHIVO
B46: 1. Ingresa tus datos en las pestañas: PRODUCCIÓN · FINANZAS · INVENTARIO · RENTABILIDAD
B47: 2. Los campos en azul son editables. Los campos en negro son fórmulas — no modificar.
B48: 3. Este dashboard (INICIO) se actualiza automáticamente.
B49: 4. Los semáforos cambian de color según los umbrales definidos en cada hoja.
B50: 5. Personaliza metas y productos desde cada hoja de datos.

Sheet PRODUCCION
B2: KAIPRO | MÓDULO DE PRODUCCIÓN — KPIs OPERATIVOS
B4: DATOS DE ENTRADA — PRODUCCIÓN MENSUAL
B5: Producto/Línea | C5: Ene | D5: Feb | E5: Mar | F5: Abr | G5: May | H5: Jun | I5: Jul | J5: Ago | K5: Sep | L5: Oct | M5: Nov | N5: Dic | O5: TOTAL | P5: PROMEDIO | Q5: EFIC.% | R5: CUMPL.%
B6: Producto A | C6: 1200 | D6: 1350 | E6: 1100 | F6: 1420 | G6: 1500 | H6: 1380 | I6: 1550 | J6: 1600 | K6: 1480 | L6: 1700 | M6: 1800 | N6: 1850 | O6: =SUM(C6:N6) -> 17930 | P6: =AVERAGE(C6:N6) -> 1494.1667
B7: Producto B | C7: 800 | D7: 820 | E7: 790 | F7: 850 | G7: 900 | H7: 880 | I7: 920 | J7: 950 | K7: 910 | L7: 980 | M7: 1020 | N7: 1050 | O7: =SUM(C7:N7) -> 10870 | P7: =AVERAGE(C7:N7) -> 905.83333
B8: Producto C | C8: 500 | D8: 480 | E8: 520 | F8: 540 | G8: 560 | H8: 530 | I8: 580 | J8: 600 | K8: 570 | L8: 620 | M8: 650 | N8: 680 | O8: =SUM(C8:N8) -> 6830 | P8: =AVERAGE(C8:N8) -> 569.16667
B9: Producto D | C9: 300 | D9: 310 | E9: 295 | F9: 320 | G9: 340 | H9: 315 | I9: 360 | J9: 370 | K9: 350 | L9: 390 | M9: 410 | N9: 420 | O9: =SUM(C9:N9) -> 4180 | P9: =AVERAGE(C9:N9) -> 348.33333 | S9: =IFERROR(SUM(C22:N22)/MAX(SUM(C23:N23),1),0) -> 0.99005223 | T9: =IFERROR(MIN(SUM(C22:N22)/SUM(C23:N23),1),0) -> 0.99005223
B10: TOTAL PRODUCCIÓN | C10: =SUM(C6:C9) -> 2800 | D10: =SUM(D6:D9) -> 2960 | E10: =SUM(E6:E9) -> 2705 | F10: =SUM(F6:F9) -> 3130 | G10: =SUM(G6:G9) -> 3300 | H10: =SUM(H6:H9) -> 3105 | I10: =SUM(I6:I9) -> 3410 | J10: =SUM(J6:J9) -> 3520 | ... P10: =SUM(P6:P9) -> 3317.5
B12: METAS DE PRODUCCIÓN
B13: Producto/Línea | C13: Ene | D13: Feb | E13: Mar | F13: Abr | G13: May | H13: Jun | I13: Jul | J13: Ago | K13: Sep | L13: Oct | M13: Nov | N13: Dic | O13: TOTAL | P13: PROMEDIO | Q13: EFIC.% | R13: CUMPL.%
B14: Meta A | C14: 1300 | D14: 1300 | E14: 1300 | F14: 1400 | G14: 1500 | H14: 1400 | I14: 1500 | J14: 1600 | K14: 1500 | L14: 1700 | M14: 1800 | N14: 1800 | O14: =SUM(C14:N14) -> 18100
B15: Meta B | C15: 850 | D15: 850 | E15: 850 | F15: 880 | G15: 900 | H15: 900 | I15: 920 | J15: 950 | K15: 940 | L15: 980 | M15: 1000 | N15: 1050 | O15: =SUM(C15:N15) -> 11070
B16: Meta C | C16: 500 | D16: 500 | E16: 520 | F16: 540 | G16: 560 | H16: 540 | I16: 580 | J16: 600 | K16: 580 | L16: 620 | M16: 650 | N16: 660 | O16: =SUM(C16:N16) -> 6850
B17: Meta D | C17: 300 | D17: 310 | E17: 300 | F17: 325 | G17: 340 | H17: 320 | I17: 355 | J17: 370 | K17: 360 | L17: 385 | M17: 410 | N17: 415 | O17: =SUM(C17:N17) -> 4190
B20: KPIs — EFICIENCIA Y CUMPLIMIENTO POR MES
B21: Producto/Línea | C21: Ene | D21: Feb | E21: Mar | F21: Abr | G21: May | H21: Jun | I21: Jul | J21: Ago | K21: Sep | L21: Oct | M21: Nov | N21: Dic | O21: TOTAL | P21: PROMEDIO | Q21: EFIC.% | R21: CUMPL.%
B22: Producción Total | C22: =C10 -> 2800 | D22: =D10 -> 2960 | E22: =E10 -> 2705 | F22: =F10 -> 3130 | G22: =G10 -> 3300 | H22: =H10 -> 3105 | I22: =I10 -> 3410 | J22: =J10 -> 3520 | ... N22: =N10 -> 4000 | O22: =SUM(C22:N22) -> 39810
B23: Meta Total | C23: =SUM(C14:C17) -> 2950 | D23: =SUM(D14:D17) -> 2960 | E23: =SUM(E14:E17) -> 2970 | F23: =SUM(F14:F17) -> 3145 | G23: =SUM(G14:G17) -> 3300 | H23: =SUM(H14:H17) -> 3160 | I23: =SUM(I14:I17) -> 3355 | J23: =SUM(J14:J17) -> 3520 | ... N23: =SUM(N14:N17) -> 3925 | O23: =SUM(C23:N23) -> 40210
B24: Diferencia | C24: =C22-C23 -> -150 | D24: =D22-D23 -> 0 | E24: =E22-E23 -> -265 | F24: =F22-F23 -> -15 | G24: =G22-G23 -> 0 | H24: =H22-H23 -> -55 | I24: =I22-I23 -> 55 | J24: =J22-J23 -> 0 | ... N24: =N22-N23 -> 75 | O24: =SUM(C24:N24) -> -400
B25: Eficiencia % | C25: =IFERROR(C22/MAX(C23,1),0) -> 0.94915254 | D25: =IFERROR(D22/MAX(D23,1),0) -> 1 | E25: =IFERROR(E22/MAX(E23,1),0) -> 0.91077441 | F25: =IFERROR(F22/MAX(F23,1),0) -> 0.99523052 | G25: =IFERROR(G22/MAX(G23,1),0) -> 1 | H25: =IFERROR(H22/MAX(H23,1),0) -> 0.98259494 | I25: =IFERROR(I22/MAX(I23,1),0) -> 1.0163934 | J25: =IFERROR(J22/MAX(J23,1),0) -> 1 | ... N25: =IFERROR(N22/MAX(N23,1),0) -> 1.0191083 | O25: =AVERAGE(C25:N25) -> 0.98825686
B26: Cumplimiento % | C26: =IFERROR(MIN(C22/C23,1),0) -> 0.94915254 | D26: =IFERROR(MIN(D22/D23,1),0) -> 1 | E26: =IFERROR(MIN(E22/E23,1),0) -> 0.91077441 | F26: =IFERROR(MIN(F22/F23,1),0) -> 0.99523052 | G26: =IFERROR(MIN(G22/G23,1),0) -> 1 | H26: =IFERROR(MIN(H22/H23,1),0) -> 0.98259494 | I26: =IFERROR(MIN(I22/I23,1),0) -> 1 | J26: =IFERROR(MIN(J22/J23,1),0) -> 1 | ... N26: =IFERROR(MIN(N22/N23,1),0) -> 1 | O26: =AVERAGE(C26:N26) -> 0.98475353
Q30: =O10*100 -> 3981000

Sheet FINANZAS
B2: KAIPRO | MÓDULO FINANCIERO — FLUJO DE CAJA Y GASTOS
B4: INGRESOS
B5: Concepto | C5: Ene | D5: Feb | E5: Mar | F5: Abr | G5: May | H5: Jun | I5: Jul | J5: Ago | K5: Sep | L5: Oct | M5: Nov | N5: Dic
B6: Ventas Producto A | C6: 120000 | D6: 132000 | E6: 115000 | F6: 140000 | G6: 150000 | H6: 138000 | I6: =H6*1.03 -> 142140 | J6: =I6*1.03 -> 146404.2 | K6: =J6*1.03 -> 150796.33 | L6: =K6*1.03 -> 155320.22 | M6: =L6*1.03 -> 159979.82 | N6: =M6*1.03 -> 164779.22
B7: Ventas Producto B | C7: 80000 | D7: 82000 | E7: 79000 | F7: 85000 | G7: 90000 | H7: 88000 | I7: =H7*1.03 -> 90640 | J7: =I7*1.03 -> 93359.2 | K7: =J7*1.03 -> 96159.976 | L7: =K7*1.03 -> 99044.775 | M7: =L7*1.03 -> 102016.12 | N7: =M7*1.03 -> 105076.6
B8: Ventas Producto C | C8: 50000 | D8: 48000 | E8: 52000 | F8: 54000 | G8: 56000 | H8: 53000 | I8: =H8*1.03 -> 54590 | J8: =I8*1.03 -> 56227.7 | K8: =J8*1.03 -> 57914.531 | L8: =K8*1.03 -> 59651.967 | M8: =L8*1.03 -> 61441.526 | N8: =M8*1.03 -> 63284.772
B9: Otros Ingresos | C9: 5000 | D9: 5000 | E9: 5000 | F9: 5000 | G9: 5000 | H9: 5000 | I9: =H9*1.03 -> 5150 | J9: =I9*1.03 -> 5304.5 | K9: =J9*1.03 -> 5463.635 | L9: =K9*1.03 -> 5627.5441 | M9: =L9*1.03 -> 5796.3704 | N9: =M9*1.03 -> 5970.2615
B10: TOTAL INGRESOS | C10: =SUM(C6:C9) -> 255000 | D10: =SUM(D6:D9) -> 267000 | E10: =SUM(E6:E9) -> 251000 | F10: =SUM(F6:F9) -> 284000 | G10: =SUM(G6:G9) -> 301000 | H10: =SUM(H6:H9) -> 284000 | I10: =SUM(I6:I9) -> 292520 | J10: =SUM(J6:J9) -> 301295.6 | ... N10: =SUM(N6:N9) -> 339110.85
B12: COSTOS Y GASTOS OPERATIVOS
B13: Concepto | C13: Ene | D13: Feb | E13: Mar | F13: Abr | G13: May | H13: Jun | I13: Jul | J13: Ago | K13: Sep | L13: Oct | M13: Nov | N13: Dic
B14: Costo de Producción | C14: 65000 | D14: 71000 | E14: 62000 | F14: 75000 | G14: 81000 | H14: 74000 | I14: =H14*1.01 -> 74740 | J14: =I14*1.01 -> 75487.4 | K14: =J14*1.01 -> 76242.274 | L14: =K14*1.01 -> 77004.697 | M14: =L14*1.01 -> 77774.744 | N14: =M14*1.01 -> 78552.491
B15: Materia Prima | C15: 30000 | D15: 33000 | E15: 29000 | F15: 35000 | G15: 38000 | H15: 34000 | I15: =H15*1.01 -> 34340 | J15: =I15*1.01 -> 34683.4 | K15: =J15*1.01 -> 35030.234 | L15: =K15*1.01 -> 35380.536 | M15: =L15*1.01 -> 35734.342 | N15: =M15*1.01 -> 36091.685
B16: Mano de Obra | C16: 18000 | D16: 18000 | E16: 18000 | F16: 18000 | G16: 18000 | H16: 18000 | I16: =H16*1.01 -> 18180 | J16: =I16*1.01 -> 18361.8 | K16: =J16*1.01 -> 18545.418 | L16: =K16*1.01 -> 18730.872 | M16: =L16*1.01 -> 18918.181 | N16: =M16*1.01 -> 19107.363
B17: Gastos Generales | C17: 8000 | D17: 8200 | E17: 8100 | F17: 8300 | G17: 8500 | H17: 8200 | I17: =H17*1.01 -> 8282 | J17: =I17*1.01 -> 8364.82 | K17: =J17*1.01 -> 8448.4682 | L17: =K17*1.01 -> 8532.9529 | M17: =L17*1.01 -> 8618.2824 | N17: =M17*1.01 -> 8704.4652
B18: Gastos Administrativos | C18: 6000 | D18: 6000 | E18: 6000 | F18: 6000 | G18: 6000 | H18: 6000 | I18: =H18*1.01 -> 6060 | J18: =I18*1.01 -> 6120.6 | K18: =J18*1.01 -> 6181.806 | L18: =K18*1.01 -> 6243.6241 | M18: =L18*1.01 -> 6306.0603 | N18: =M18*1.01 -> 6369.1209
B19: Gastos de Ventas | C19: 5000 | D19: 5200 | E19: 4800 | F19: 5500 | G19: 5800 | H19: 5300 | I19: =H19*1.01 -> 5353 | J19: =I19*1.01 -> 5406.53 | K19: =J19*1.01 -> 5460.5953 | L19: =K19*1.01 -> 5515.2013 | M19: =L19*1.01 -> 5570.3533 | N19: =M19*1.01 -> 5626.0568
B20: Depreciación | C20: 2500 | D20: 2500 | E20: 2500 | F20: 2500 | G20: 2500 | H20: 2500 | I20: =H20*1.01 -> 2525 | J20: =I20*1.01 -> 2550.25 | K20: =J20*1.01 -> 2575.7525 | L20: =K20*1.01 -> 2601.51 | M20: =L20*1.01 -> 2627.5251 | N20: =M20*1.01 -> 2653.8004
B21: TOTAL COSTOS | C21: =SUM(C14:C20) -> 134500 | D21: =SUM(D14:D20) -> 143900 | E21: =SUM(E14:E20) -> 130400 | F21: =SUM(F14:F20) -> 150300 | G21: =SUM(G14:G20) -> 159800 | H21: =SUM(H14:H20) -> 148000 | I21: =SUM(I14:I20) -> 149480 | J21: =SUM(J14:J20) -> 150974.8 | ... N21: =SUM(N14:N20) -> 157104.98
B23: RESULTADOS
B24: Utilidad Bruta | C24: =C10-C14 -> 190000 | D24: =D10-D14 -> 196000 | E24: =E10-E14 -> 189000 | F24: =F10-F14 -> 209000 | G24: =G10-G14 -> 220000 | H24: =H10-H14 -> 210000 | I24: =I10-I14 -> 217780 | J24: =J10-J14 -> 225808.2 | ... N24: =N10-N14 -> 260558.36
B25: Margen Bruto % | C25: =IFERROR((C10-C14)/C10,0) -> 0.74509804 | D25: =IFERROR((D10-D14)/D10,0) -> 0.7340824 | E25: =IFERROR((E10-E14)/E10,0) -> 0.75298805 | F25: =IFERROR((F10-F14)/F10,0) -> 0.73591549 | G25: =IFERROR((G10-G14)/G10,0) -> 0.73089701 | H25: =IFERROR((H10-H14)/H10,0) -> 0.73943662 | I25: =IFERROR((I10-I14)/I10,0) -> 0.7444961 | J25: =IFERROR((J10-J14)/J10,0) -> 0.74945734 | ... N25: =IFERROR((N10-N14)/N10,0) -> 0.76835748
B26: EBITDA | C26: =C10-C21+C20 -> 123000 | D26: =D10-D21+D20 -> 125600 | E26: =E10-E21+E20 -> 123100 | F26: =F10-F21+F20 -> 136200 | G26: =G10-G21+G20 -> 143700 | H26: =H10-H21+H20 -> 138500 | I26: =I10-I21+I20 -> 145565 | J26: =J10-J21+J20 -> 152871.05 | ... N26: =N10-N21+N20 -> 184659.67
B27: Utilidad Neta | C27: =C10-C21 -> 120500 | D27: =D10-D21 -> 123100 | E27: =E10-E21 -> 120600 | F27: =F10-F21 -> 133700 | G27: =G10-G21 -> 141200 | H27: =H10-H21 -> 136000 | I27: =I10-I21 -> 143040 | J27: =J10-J21 -> 150320.8 | ... N27: =N10-N21 -> 182005.87
B28: Margen Neto % | C28: =IFERROR((C10-C21)/C10,0) -> 0.47254902 | D28: =IFERROR((D10-D21)/D10,0) -> 0.46104869 | E28: =IFERROR((E10-E21)/E10,0) -> 0.48047809 | F28: =IFERROR((F10-F21)/F10,0) -> 0.47077465 | G28: =IFERROR((G10-G21)/G10,0) -> 0.46910299 | H28: =IFERROR((H10-H21)/H10,0) -> 0.47887324 | I28: =IFERROR((I10-I21)/I10,0) -> 0.48899221 | J28: =IFERROR((J10-J21)/J10,0) -> 0.49891469 | ... N28: =IFERROR((N10-N21)/N10,0) -> 0.53671497
B29: Flujo Neto Caja | C29: =C10-C21+C20 -> 123000 | D29: =D10-D21+D20 -> 125600 | E29: =E10-E21+E20 -> 123100 | F29: =F10-F21+F20 -> 136200 | G29: =G10-G21+G20 -> 143700 | H29: =H10-H21+H20 -> 138500 | I29: =I10-I21+I20 -> 145565 | J29: =J10-J21+J20 -> 152871.05 | ... N29: =N10-N21+N20 -> 184659.67
E35: =SUM(C25:N25) -> 8.977914
E38: =SUM(C29:N29) -> 1778169.9

Sheet INVENTARIO
B2: KAIPRO | CONTROL DE INVENTARIO Y ROTACIÓN
B4: INVENTARIO ACTUAL — VALORIZADO
B5: Producto/Material | C5: Categoría | D5: Stock Actual | E5: Stock Mín | F5: Stock Máx | G5: Costo Unitario | H5: Valor Total | I5: Rotación (veces) | J5: Cobertura (días) | K5: Estado
B6: Materia Prima A | C6: Insumo | D6: 850 | E6: 200 | F6: 1200 | G6: 12.5 | H6: =D6*G6 -> 10625 | I6: =IFERROR((D6*4)/((E6+F6)/2),0) -> 4.8571429 | J6: =IFERROR(D6/(D6*4/365),0) -> 91.25 | K6: =IF(D6<E6,"🔴 BAJO",IF(D6>F6,"🟡 EXCESO","🟢 OK")) -> 🟢 OK
B7: Materia Prima B | C7: Insumo | D7: 420 | E7: 100 | F7: 600 | G7: 8.75 | H7: =D7*G7 -> 3675 | I7: =IFERROR((D7*4)/((E7+F7)/2),0) -> 4.8 | J7: =IFERROR(D7/(D7*4/365),0) -> 91.25 | K7: =IF(D7<E7,"🔴 BAJO",IF(D7>F7,"🟡 EXCESO","🟢 OK")) -> 🟢 OK
B8: Producto A PT | C8: PT | D8: 320 | E8: 80 | F8: 500 | G8: 45 | H8: =D8*G8 -> 14400 | I8: =IFERROR((D8*4)/((E8+F8)/2),0) -> 4.4137931 | J8: =IFERROR(D8/(D8*4/365),0) -> 91.25 | K8: =IF(D8<E8,"🔴 BAJO",IF(D8>F8,"🟡 EXCESO","🟢 OK")) -> 🟢 OK
B9: Producto B PT | C9: PT | D9: 185 | E9: 50 | F9: 300 | G9: 38.5 | H9: =D9*G9 -> 7122.5 | I9: =IFERROR((D9*4)/((E9+F9)/2),0) -> 4.2285714 | J9: =IFERROR(D9/(D9*4/365),0) -> 91.25 | K9: =IF(D9<E9,"🔴 BAJO",IF(D9>F9,"🟡 EXCESO","🟢 OK")) -> 🟢 OK
B10: Producto C PT | C10: PT | D10: 240 | E10: 60 | F10: 400 | G10: 28 | H10: =D10*G10 -> 6720 | I10: =IFERROR((D10*4)/((E10+F10)/2),0) -> 4.173913 | J10: =IFERROR(D10/(D10*4/365),0) -> 91.25 | K10: =IF(D10<E10,"🔴 BAJO",IF(D10>F10,"🟡 EXCESO","🟢 OK")) -> 🟢 OK
B11: Embalaje Cajas | C11: Empaque | D11: 1200 | E11: 300 | F11: 2000 | G11: 1.2 | H11: =D11*G11 -> 1440 | I11: =IFERROR((D11*4)/((E11+F11)/2),0) -> 4.173913 | J11: =IFERROR(D11/(D11*4/365),0) -> 91.25 | K11: =IF(D11<E11,"🔴 BAJO",IF(D11>F11,"🟡 EXCESO","🟢 OK")) -> 🟢 OK
B12: Embalaje Bolsas | C12: Empaque | D12: 3500 | E12: 800 | F12: 5000 | G12: 0.45 | H12: =D12*G12 -> 1575 | I12: =IFERROR((D12*4)/((E12+F12)/2),0) -> 4.8275862 | J12: =IFERROR(D12/(D12*4/365),0) -> 91.25 | K12: =IF(D12<E12,"🔴 BAJO",IF(D12>F12,"🟡 EXCESO","🟢 OK")) -> 🟢 OK
B13: Repuesto Equipo A | C13: Repuesto | D13: 12 | E13: 3 | F13: 20 | G13: 280 | H13: =D13*G13 -> 3360 | I13: =IFERROR((D13*4)/((E13+F13)/2),0) -> 4.173913 | J13: =IFERROR(D13/(D13*4/365),0) -> 91.25 | K13: =IF(D13<E13,"🔴 BAJO",IF(D13>F13,"🟡 EXCESO","🟢 OK")) -> 🟢 OK
B14: Repuesto Equipo B | C14: Repuesto | D14: 8 | E14: 2 | F14: 15 | G14: 195 | H14: =D14*G14 -> 1560 | I14: =IFERROR((D14*4)/((E14+F14)/2),0) -> 3.7647059 | J14: =IFERROR(D14/(D14*4/365),0) -> 91.25 | K14: =IF(D14<E14,"🔴 BAJO",IF(D14>F14,"🟡 EXCESO","🟢 OK")) -> 🟢 OK
B15: Suministros Ofic. | C15: Admin | D15: 450 | E15: 100 | F15: 600 | G15: 2.3 | H15: =D15*G15 -> 1035 | I15: =IFERROR((D15*4)/((E15+F15)/2),0) -> 5.1428571 | J15: =IFERROR(D15/(D15*4/365),0) -> 91.25 | K15: =IF(D15<E15,"🔴 BAJO",IF(D15>F15,"🟡 EXCESO","🟢 OK")) -> 🟢 OK
B16: TOTAL INVENTARIO | H16: =SUM(H6:H15) -> 51512.5 | I16: =AVERAGE(I6:I15) -> 4.4556396 | J16: =AVERAGE(J6:J15) -> 91.25
B18: ⚠ ALERTAS DE REABASTECIMIENTO
B19: =IFERROR(COUNTIF(K6:K15,"*BAJO*")&" productos bajo stock mínimo — revisar urgente","") -> 0 productos bajo stock mínimo — revisar urgente
F32: =H16 -> 51512.5 | G32: =I16 -> 4.4556396 | H32: =J16 -> 91.25

Sheet RENTABILIDAD
B2: KAIPRO | RENTABILIDAD POR PRODUCTO Y CLIENTE
B4: ANÁLISIS DE RENTABILIDAD POR PRODUCTO
B5: Producto | C5: Precio Venta | D5: Costo Producción | E5: Costo Distrib. | F5: Costo Total | G5: Margen $ | H5: Margen % | I5: Clasificación
B6: Producto A | C6: 85 | D6: 52 | E6: 4.5 | F6: =D6+E6 -> 56.5 | G6: =C6-F6 -> 28.5 | H6: =IFERROR(G6/C6,0) -> 0.33529412 | I6: =IF(H6>=0.35,"⭐ ESTRELLA",IF(H6>=0.2,"✔ BUENO",IF(H6>=0.1,"⚠ REGULAR","✘ REVISAR"))) -> ✔ BUENO
B7: Producto B | C7: 65 | D7: 38 | E7: 3.8 | F7: =D7+E7 -> 41.8 | G7: =C7-F7 -> 23.2 | H7: =IFERROR(G7/C7,0) -> 0.35692308 | I7: =IF(H7>=0.35,"⭐ ESTRELLA",IF(H7>=0.2,"✔ BUENO",IF(H7>=0.1,"⚠ REGULAR","✘ REVISAR"))) -> ⭐ ESTRELLA
B8: Producto C | C8: 45 | D8: 28 | E8: 2.5 | F8: =D8+E8 -> 30.5 | G8: =C8-F8 -> 14.5 | H8: =IFERROR(G8/C8,0) -> 0.32222222 | I8: =IF(H8>=0.35,"⭐ ESTRELLA",IF(H8>=0.2,"✔ BUENO",IF(H8>=0.1,"⚠ REGULAR","✘ REVISAR"))) -> ✔ BUENO
B9: Producto D | C9: 32 | D9: 22 | E9: 1.8 | F9: =D9+E9 -> 23.8 | G9: =C9-F9 -> 8.2 | H9: =IFERROR(G9/C9,0) -> 0.25625 | I9: =IF(H9>=0.35,"⭐ ESTRELLA",IF(H9>=0.2,"✔ BUENO",IF(H9>=0.1,"⚠ REGULAR","✘ REVISAR"))) -> ✔ BUENO
B10: Producto E | C10: 120 | D10: 65 | E10: 6 | F10: =D10+E10 -> 71 | G10: =C10-F10 -> 49 | H10: =IFERROR(G10/C10,0) -> 0.40833333 | I10: =IF(H10>=0.35,"⭐ ESTRELLA",IF(H10>=0.2,"✔ BUENO",IF(H10>=0.1,"⚠ REGULAR","✘ REVISAR"))) -> ⭐ ESTRELLA
B11: Producto F | C11: 28 | D11: 21 | E11: 1.2 | F11: =D11+E11 -> 22.2 | G11: =C11-F11 -> 5.8 | H11: =IFERROR(G11/C11,0) -> 0.20714286 | I11: =IF(H11>=0.35,"⭐ ESTRELLA",IF(H11>=0.2,"✔ BUENO",IF(H11>=0.1,"⚠ REGULAR","✘ REVISAR"))) -> ✔ BUENO
B12: PROMEDIO | C12: =AVERAGE(C6:C11) -> 62.5 | D12: =AVERAGE(D6:D11) -> 37.666667 | E12: =AVERAGE(E6:E11) -> 3.3 | F12: =AVERAGE(F6:F11) -> 40.966667 | G12: =AVERAGE(G6:G11) -> 21.533333 | H12: =AVERAGE(H6:H11) -> 0.31436093
B15: ANÁLISIS PARETO — TOP PRODUCTOS POR MARGEN $
B16: Producto | C16: Margen $ | D16: Margen % | E16: % Acumulado | F16: Categoría Pareto
B17: Producto E | C17: 55 | D17: =C17/SUM($C$17:$C$22) -> 0.36912752 | E17: =D17 -> 0.36912752 | F17: =IF(E17<=0.8,"🔵 VITAL (80%)","⚪ TRIVIAL (20%)") -> 🔵 VITAL (80%)
B18: Producto A | C18: 33 | D18: =C18/SUM($C$17:$C$22) -> 0.22147651 | E18: =E17+D18 -> 0.59060403 | F18: =IF(E18<=0.8,"🔵 VITAL (80%)","⚪ TRIVIAL (20%)") -> 🔵 VITAL (80%)
B19: Producto B | C19: 27 | D19: =C19/SUM($C$17:$C$22) -> 0.18120805 | E19: =E18+D19 -> 0.77181208 | F19: =IF(E19<=0.8,"🔵 VITAL (80%)","⚪ TRIVIAL (20%)") -> 🔵 VITAL (80%)
B20: Producto C | C20: 17 | D20: =C20/SUM($C$17:$C$22) -> 0.11409396 | E20: =E19+D20 -> 0.88590604 | F20: =IF(E20<=0.8,"🔵 VITAL (80%)","⚪ TRIVIAL (20%)") -> ⚪ TRIVIAL (20%)
B21: Producto D | C21: 10 | D21: =C21/SUM($C$17:$C$22) -> 0.067114094 | E21: =E20+D21 -> 0.95302013 | F21: =IF(E21<=0.8,"🔵 VITAL (80%)","⚪ TRIVIAL (20%)") -> ⚪ TRIVIAL (20%)
B22: Producto F | C22: 7 | D22: =C22/SUM($C$17:$C$22) -> 0.046979866 | E22: =E21+D22 -> 1 | F22: =IF(E22<=0.8,"🔵 VITAL (80%)","⚪ TRIVIAL (20%)") -> ⚪ TRIVIAL (20%)
H25: =AVERAGE(H6:H11) -> 0.31436093
H28: =AVERAGE(G6:G11)/AVERAGE(C6:C11) -> 0.34453333

Sheet CONFIGURACION
B2: KAIPRO | CONFIGURACIÓN GENERAL Y SUPUESTOS
B4: ▸ Todos los campos en azul son editables
B5: Parámetro | C5: Valor | D5: Descripción
B6: ── EMPRESA ──
B7: Nombre de la empresa | C7: Mi Empresa S.A. | D7: Editar con nombre real
B8: RUC / NIT | C8: 0000000000001 | D8: Editar
B9: Sector / Industria | C9: Manufactura | D9: Editar
B10: Moneda | C10: USD | D10: USD / EUR / etc.
B11: Año fiscal | C11: 2026 | D11: Año en curso
B13: ── SUPUESTOS FINANCIEROS ──
B14: Tasa de crecimiento ventas | C14: 0.03 | D14: % mensual proyectado
B15: Tasa de crecimiento costos | C15: 0.01 | D15: % mensual proyectado
B16: Impuesto a la renta | C16: 0.25 | D16: 25% por defecto
B17: Tasa de descuento (WACC) | C17: 0.12 | D17: 12% anual
B19: ── UMBRALES SEMÁFORO ──
B20: Eficiencia verde (>=) | C20: 0.85 | D20: 85% o más
B21: Eficiencia amarillo (>=) | C21: 0.75 | D21: 75% - 84%
B22: Margen verde (>=) | C22: 0.35 | D22: 35% o más
B23: Margen amarillo (>=) | C23: 0.25 | D23: 25% - 34%
B24: Rotación verde (>=) | C24: 4 | D24: 4 veces o más
B25: Rotación amarillo (>=) | C25: 2.5 | D25: 2.5 - 3.9 veces
